basilisk/__init__.py
basilisk/basilisk.cpython-311-x86_64-linux-gnu.so
basilisk/basilisk.pyi
basilisk/basilisk/__init__.pyi
basilisk/basilisk/forces.pyi
basilisk/basilisk/key.pyi
basilisk/shaders/default.frag
basilisk/shaders/default.vert
basilisk/shaders/default2D.frag
basilisk/shaders/default2D.vert
basilisk/shaders/frame.frag
basilisk/shaders/frame.vert
basilisk/shaders/instance.frag
basilisk/shaders/instance.vert
basilisk/shaders/instance2D.frag
basilisk/shaders/instance2D.vert
basilisk/shaders/skybox.frag
basilisk/shaders/skybox.vert
basilisk/shaders/test.frag
basilisk/shaders/test.vert
basilisk/shaders/include/blinn_phong.glsl
basilisk/shaders/include/light.glsl
basilisk/shaders/include/material.glsl
basilisk/shaders/include/texture.glsl
basilisk_engine.libs/libGLX-c14481bc.so.0.0.0
basilisk_engine.libs/libGLdispatch-64b28464.so.0.0.0
basilisk_engine.libs/libOpenGL-4c5f8d52.so.0.0.0
include/GLFW/glfw3.h
include/GLFW/glfw3native.h
lib64/libglfw3.a
lib64/cmake/glfw3/glfw3Config.cmake
lib64/cmake/glfw3/glfw3ConfigVersion.cmake
lib64/cmake/glfw3/glfw3Targets-release.cmake
lib64/cmake/glfw3/glfw3Targets.cmake
lib64/pkgconfig/glfw3.pc
basilisk_engine-0.2.10.dist-info/METADATA
basilisk_engine-0.2.10.dist-info/WHEEL
basilisk_engine-0.2.10.dist-info/RECORD
basilisk_engine-0.2.10.dist-info/sboms/auditwheel.cdx.json
