Metadata-Version: 2.2
Name: basilisk-engine
Version: 0.2.10
Summary: Python bindings for the Basilisk C++ library
Keywords: graphics,game-engine,3d,2d,opengl,physics,simulation,rendering
Author-Email: Jonah Coffelt <coffelt.jonah0918@gmail.com>, Isaac Lagoy <isaacblagoy@gmail.com>
Maintainer-Email: Jonah Coffelt <coffelt.jonah0918@gmail.com>, Isaac Lagoy <isaacblagoy@gmail.com>
License: MIT
Classifier: Development Status :: 4 - Beta
Classifier: Intended Audience :: Developers
Classifier: License :: OSI Approved :: MIT License
Classifier: Operating System :: MacOS :: MacOS X
Classifier: Operating System :: Microsoft :: Windows
Classifier: Operating System :: POSIX :: Linux
Classifier: Programming Language :: Python :: 3
Classifier: Programming Language :: Python :: 3.9
Classifier: Programming Language :: Python :: 3.10
Classifier: Programming Language :: Python :: 3.11
Classifier: Programming Language :: Python :: 3.12
Classifier: Programming Language :: C++
Classifier: Topic :: Multimedia :: Graphics
Classifier: Topic :: Software Development :: Libraries :: Python Modules
Classifier: Topic :: Games/Entertainment
Project-URL: Homepage, https://github.com/BasiliskGroup/BasiliskEngine
Project-URL: Repository, https://github.com/BasiliskGroup/BasiliskEngine
Project-URL: Documentation, https://github.com/BasiliskGroup/BasiliskEngine#readme
Project-URL: Bug Tracker, https://github.com/BasiliskGroup/BasiliskEngine/issues
Requires-Python: >=3.9
